<?xml version="1.0" encoding="UTF-8"?><law><structure><unit label="title" identifier="XII" order_by="12">CONSERVATION AND STATE DEVELOPMENT</unit><unit label="chapter" identifier="147" order_by="147">STATE AND AREA PLANNING -- REGIONAL DEVELOPMENT </unit></structure><section_number>147.680</section_number><catch_line>Prohibition of construction by public agency without commission's review and recommendations. </catch_line><order_by>680</order_by><text>No public agency shall construct or authorize the construction of any public facility, which is determined by the area planning commission to be of area-wide significance, within the area planning boundaries until and unless the proposed location and extent of such public construction or authorization shall have been reviewed and recommendations made to the appropriate public agency by the area planning commission. </text><history>Amended 1982 Ky. Acts ch. 253, sec. 9, effective July 15, 1982, -- Amended 1974 Ky. Acts ch. 359, sec. 4. -- Created 1960 Ky. Acts ch. 248, sec. 8, effective June 16, 1960. </history><metadata><effective>July 15, 1982 </effective><pdf-author>ganesan_m</pdf-author><pdf-creation-date>2015-07-01</pdf-creation-date><pdf-download-date>2016-03-18 12:16:59</pdf-download-date><original-link>http://www.lrc.ky.gov/statutes/statute.aspx?id=1628</original-link></metadata><tags><tag>computer-parsed</tag><tag>unverified</tag></tags></law>