<?xml version="1.0" encoding="UTF-8"?><law><structure><unit label="title" identifier="XXVII" order_by="27">LABOR AND HUMAN RIGHTS</unit><unit label="chapter" identifier="342" order_by="342">WORKERS' COMPENSATION </unit></structure><section_number>342.390</section_number><catch_line>Employer's election to operate under chapter </catch_line><order_by>390</order_by><text>Election to operate under this chapter if an employer is not mandatorily subject to the chapter shall be effected by the employer purchasing workers' compensation insurance or qualifying as a self insured. The proof of election shall be the proof of insurance coverage provided for in KRS 342.340(2). </text><history>  Amended 1976 Ky. Acts ch. 160, sec. 7. -- Amended 1968 Ky. Acts ch. 159, sec. 2. -- Recodified 1942 Ky. Acts ch. 208, sec. 1, effective October 1, 1942, from Ky. Stat. sec. 4956. </history><metadata><pdf-author>ganesan_m</pdf-author><pdf-creation-date>2015-07-02</pdf-creation-date><pdf-download-date>2016-03-18 12:15:50</pdf-download-date><original-link>http://www.lrc.ky.gov/statutes/statute.aspx?id=32494</original-link></metadata><tags><tag>computer-parsed</tag><tag>unverified</tag></tags></law>