<?xml version="1.0" encoding="UTF-8"?><law><structure><unit label="title" identifier="L" order_by="50">KENTUCKY PENAL CODE</unit><unit label="chapter" identifier="534" order_by="534">FINES </unit></structure><section_number>534.010</section_number><catch_line>Definition. </catch_line><order_by>010</order_by><text>The following definition applies in this chapter unless the context otherwise requires:   "Gain" means the amount of money or the value of property derived from the commission of the crime, less the amount of money or the value of property returned to the victim of the crime or seized by or surrendered to lawful authority prior to the time sentence is imposed.  </text><history>Created 1974 Ky. Acts ch. 406, sec. 290, effective January 1, 1975. </history><metadata><effective>January 1, 1975. </effective><pdf-author>ganesan_m</pdf-author><pdf-creation-date>2015-07-02</pdf-creation-date><pdf-download-date>2016-03-18 12:15:19</pdf-download-date><original-link>http://www.lrc.ky.gov/statutes/statute.aspx?id=20095</original-link></metadata><tags><tag>computer-parsed</tag><tag>unverified</tag></tags></law>