<?xml version="1.0" encoding="UTF-8"?><law><structure><unit label="title" identifier="XXIX" order_by="29">COMMERCE AND TRADE</unit><unit label="chapter" identifier="367" order_by="367">CONSUMER PROTECTION </unit></structure><section_number>367.97537</section_number><catch_line>Crematory licensure and regulation fund. </catch_line><order_by>97537</order_by><text>There is hereby created a trust and agency account in the State Treasury to be known as the "Crematory Licensure and Regulation Fund," which shall consist of all moneys received from fees under KRS 367.97504, from civil penalties assessed under this section, and from earnings on investments of these fees and civil penalties. The funds in this account shall not lapse and shall be continuously appropriated to the Attorney General for the administration of KRS 367.97501 to 367.97537. </text><history> Created 1994 Ky. Acts ch. 140, sec. 12, effective July 15, 1994. </history><metadata><effective> July 15, 1994 </effective><pdf-author>ganesan_m</pdf-author><pdf-creation-date>2015-07-02</pdf-creation-date><pdf-download-date>2016-03-18 12:15:41</pdf-download-date><original-link>http://www.lrc.ky.gov/statutes/statute.aspx?id=35147</original-link></metadata><tags><tag>computer-parsed</tag><tag>unverified</tag></tags></law>