<?xml version="1.0" encoding="UTF-8"?><law><structure><unit label="title" identifier="II" order_by="2">LEGISLATIVE BRANCH</unit><unit label="chapter" identifier="6" order_by="6">THE GENERAL ASSEMBLY </unit></structure><section_number>6.070</section_number><catch_line>Contempt or breach of privilege, punishment for. </catch_line><order_by>070</order_by><text>Either house of the General Assembly may punish anyone by fine not exceeding five hundred dollars ($500) or by imprisonment not exceeding six (6) months, or both, for a breach of privilege, or for any contempt except the offenses described in KRS 6.080, which shall be punished as provided in KRS 6.080 to 6.131. Contempts and breaches of privilege shall be inquired into first by a special committee, before which the accused shall have the right to be heard by himself and counsel, and have compulsory process to procure the attendance of his witnesses. The committee shall report all matters of fact specially, with its opinion, for the final action of the house. </text><history>Recodified 1942 Ky. Acts ch. 208, sec. 1, effective October 1, 1942, from Ky. Stat. sec. 1982. </history><metadata><effective>October 1, 1942</effective><pdf-author>ganesan_m</pdf-author><pdf-creation-date>2015-07-01</pdf-creation-date><pdf-download-date>2016-03-18 12:15:14</pdf-download-date><original-link>http://www.lrc.ky.gov/statutes/statute.aspx?id=254</original-link></metadata><tags><tag>computer-parsed</tag><tag>unverified</tag></tags></law>