<?xml version="1.0" encoding="UTF-8"?><law><structure><unit label="title" identifier="XXXI" order_by="31">DEBTOR-CREDITOR RELATIONS</unit><unit label="chapter" identifier="378" order_by="378">FRAUDULENT AND PREFERENTIAL CONVEYANCES </unit></structure><section_number>378.020</section_number><catch_line>378.020 repealed</catch_line><order_by>020</order_by><text>Repealed, 2016.</text><history>Repealed 2015 Ky. Acts ch. 37, sec. 16, effective January 1, 2016. --Recodified 1942 Ky. Acts ch. 208, sec. 1, effective October 1, 1942, from Ky.Stat. sec. 1907.</history><metadata><catchline-at-repeal>Conveyance or encumbrance without consideration -- Effect.</catchline-at-repeal><effective>January 1, 2016</effective><pdf-author></pdf-author><pdf-creation-date></pdf-creation-date><pdf-download-date>2016-03-18 12:15:39</pdf-download-date><original-link>http://www.lrc.ky.gov/statutes/statute.aspx?id=44737</original-link></metadata><tags><tag>computer-parsed</tag><tag>unverified</tag></tags></law>