<?xml version="1.0" encoding="UTF-8"?><law><structure><unit label="title" identifier="XV" order_by="15">ROADS, WATERWAYS, AND AVIATION</unit><unit label="chapter" identifier="175" order_by="175">A COUNTY TURNPIKE AUTHORITY (Superseded) </unit></structure><section_number>175A.010</section_number><catch_line>175A.010 repealed</catch_line><order_by>010</order_by><text>Repealed, 1984. </text><history>Repealed 1984 Ky. Acts ch. 4, sec. 3, effective July 15, 1986. -- Created 1972 Ky. Acts ch. 145, sec. 1, effective June 16, 1972. </history><metadata><catchline-at-repeal>  Definitions.</catchline-at-repeal><pdf-author>ganesan_m</pdf-author><pdf-creation-date>2015-07-02</pdf-creation-date><pdf-download-date>2016-03-18 12:16:46</pdf-download-date><original-link>http://www.lrc.ky.gov/statutes/statute.aspx?id=5111</original-link></metadata><tags><tag>computer-parsed</tag><tag>unverified</tag></tags></law>