<?xml version="1.0" encoding="UTF-8"?><law><structure><unit label="title" identifier="XXV" order_by="25">BUSINESS AND FINANCIAL INSTITUTIONS</unit><unit label="chapter" identifier="" order_by=""></unit></structure><section_number>304.5-100</section_number><catch_line>"Mortgage guaranty insurance" defined. </catch_line><order_by>5-100</order_by><text>"Mortgage guaranty insurance" is insurance against financial loss by reason of nonpayment of principal, interest, rent or other sums agreed to be paid under the terms of any note, bond, lease, or other evidence of indebtedness constituting a charge on real estate, or secured by mortgage, deed of trust, or other instrument constituting a lien on real estate.  </text><history>Created 1970 Ky. Acts ch. 301, subtit. 5, sec. 10, effective June 18, 1970. </history><metadata><effective>June 18, 1970</effective><pdf-author>ganesan_m</pdf-author><pdf-creation-date>2015-07-02</pdf-creation-date><pdf-download-date>2016-03-18 12:16:08</pdf-download-date><original-link>http://www.lrc.ky.gov/statutes/statute.aspx?id=16762</original-link></metadata><tags><tag>computer-parsed</tag><tag>unverified</tag></tags></law>