<?xml version="1.0" encoding="UTF-8"?><law><structure><unit label="title" identifier="XLII" order_by="42">MISCELLANEOUS PRACTICE PROVISIONS</unit><unit label="chapter" identifier="454" order_by="454">MISCELLANEOUS CIVIL PRACTICE PROVISIONS </unit></structure><section_number>454.180</section_number><catch_line>Officer may require affidavit of surety's qualifications. </catch_line><order_by>180</order_by><text>An officer whose duty it is to take a surety in any bond provided for by any statute derived from the former Civil Code, or by the Rules of Civil Procedure may require the person offered as surety to make affidavit of his qualifications, which affidavit may be made before such officer. The taking of such an affidavit shall not exempt the officer from any liability to which he might otherwise be subject for taking insufficient security.  </text><history>Transferred 1952 Ky. Acts ch. 84, sec. 1, effective July 1, 1953, from C.C. sec. 683. </history><metadata><effective>July 1, 1953</effective><pdf-author>ganesan_m</pdf-author><pdf-creation-date>2015-07-02</pdf-creation-date><pdf-download-date>2016-03-18 12:15:24</pdf-download-date><original-link>http://www.lrc.ky.gov/statutes/statute.aspx?id=19599</original-link></metadata><tags><tag>computer-parsed</tag><tag>unverified</tag></tags></law>