<?xml version="1.0" encoding="UTF-8"?><law><structure><unit label="title" identifier="IX" order_by="9">COUNTIES, CITIES, AND OTHER LOCAL UNITS</unit><unit label="chapter" identifier="74" order_by="74">WATER DISTRICTS </unit></structure><section_number>74.140</section_number><catch_line>Acceptance of report -- Notice -- Final hearing. </catch_line><order_by>140</order_by><text>When the final report is completed and filed, it shall be examined by the county judge/executive, and if it is found to be sufficient it shall be accepted. If it is not sufficient, it may be referred back to the commission with instructions to secure further information, to be reported at a subsequent date fixed by the county judge/executive. When the report is fully completed and accepted by the county judge/executive, a date not less than twenty (20) days thereafter shall be fixed by the county judge/executive for the final hearing upon the report, and notice of the hearing shall be given by publication pursuant to KRS Chapter 424. During that time, a copy of the report shall be on file in the office of the county clerk, and shall be open to the inspection of any landowner or person interested within the district. Any landowner assessed therein may file exception to the report. The county judge/executive upon final hearing shall confirm or reject the report. </text><history>Amended 1978 Ky. Acts ch. 384, sec. 184, effective June 17, 1978. -- Amended 1966 Ky. Acts ch. 239, sec. 21. -- Recodified 1942 Ky. Acts ch. 208, sec. 1, effective October 1, 1942, from Ky. Stat. sec. 938g-9. </history><metadata><effective>June 17, 1978</effective><pdf-author>ganesan_m</pdf-author><pdf-creation-date>2015-07-16</pdf-creation-date><pdf-download-date>2016-03-18 12:17:15</pdf-download-date><original-link>http://www.lrc.ky.gov/statutes/statute.aspx?id=24378</original-link></metadata><tags><tag>computer-parsed</tag><tag>unverified</tag></tags></law>