<?xml version="1.0" encoding="UTF-8"?><law><structure><unit label="title" identifier="XXXI" order_by="31">DEBTOR-CREDITOR RELATIONS</unit><unit label="chapter" identifier="379" order_by="379">VOLUNTARY ASSIGNMENTS </unit></structure><section_number>379.120</section_number><catch_line>Allowance or rejection of claims by assignee -- Report to court -- Exceptions -- Court determination. </catch_line><order_by>120</order_by><text>The assignee may administer oaths and examine witnesses concerning claims, and may allow or refuse to allow any claim or part thereof. He shall file in the District Court, within six (6) months after his appointment and every three (3) months thereafter until discharged, a list of all claims presented to him, together with his reasons for refusing any claim not allowed, and sixty (60) days thereafter the report shall be confirmed unless exceptions to it are filed. Any creditor may file exceptions to the report because of the failure to allow his claim, or because of the allowance of any claim, and the court shall hear and determine the exceptions. </text><history>Amended 1976 (1st Extra. Sess.) Ky. Acts ch. 14, sec. 297, effective January 2, 1978. -- Recodified 1942 Ky. Acts ch. 208, sec. 1, effective October 1, 1942, from Ky. Stat. sec. 91. </history><metadata><effective>January 2, 1978</effective><pdf-author>ganesan_m</pdf-author><pdf-creation-date>2015-07-02</pdf-creation-date><pdf-download-date>2016-03-18 12:15:43</pdf-download-date><original-link>http://www.lrc.ky.gov/statutes/statute.aspx?id=35372</original-link></metadata><tags><tag>computer-parsed</tag><tag>unverified</tag></tags></law>