<?xml version="1.0" encoding="UTF-8"?><law><structure><unit label="title" identifier="XVIII" order_by="18">PUBLIC HEALTH</unit><unit label="chapter" identifier="224" order_by="224">A KENTUCKY INFRASTRUCTURE AUTHORITY </unit></structure><section_number>224A.050</section_number><catch_line>Use of funds. </catch_line><order_by>050</order_by><text>It is hereby found and declared as a legislative finding of fact that in performing its duties and responsibilities, the authority is performing and carrying out essential governmental functions. The authority may, from time to time, receive and accept any and all appropriations to the authority which may be made by the General Assembly of the state, and the appropriations may be made to the authority. The authority may, from time to time, receive and accept from the state, its agencies, and any federal agency, grants for, or in aid of, any infrastructure project, and grants for, or in aid of, research or management studies or training projects related to the purposes for which the authority is created, the grants or contributions to be held, used, and applied only for the purposes for which the grants and contributions are made and received. </text><history>Amended 1988 Ky. Acts ch. 124, sec. 6, effective March 31, 1988. -- Created 1972 Ky. Acts ch. 329, sec. 5. </history><metadata><effective>March 31, 1988 </effective><pdf-author>ganesan_m</pdf-author><pdf-creation-date>2015-07-02</pdf-creation-date><pdf-download-date>2016-03-18 12:16:31</pdf-download-date><original-link>http://www.lrc.ky.gov/statutes/statute.aspx?id=10557</original-link></metadata><tags><tag>computer-parsed</tag><tag>unverified</tag></tags></law>