<?xml version="1.0" encoding="UTF-8"?><law><structure><unit label="title" identifier="XVIII" order_by="18">PUBLIC HEALTH</unit><unit label="chapter" identifier="217" order_by="217">FOODS, DRUGS, AND POISONS </unit></structure><section_number>217.640</section_number><catch_line>Jurisdiction vested in department -- Repealing clause. </catch_line><order_by>640</order_by><text>Jurisdiction in all matters pertaining to the distribution, sale and transportation of pesticides is by KRS 217.542 to 217.640 vested exclusively in the department and all acts and parts of acts inconsistent with KRS 217.542 to 217.640 are hereby expressly repealed including the provisions of KRS 217.400 which cover economic poisons subject to KRS 217.542 to 217.640. </text><history>Amended 1980 Ky. Acts ch. 188, sec. 217, effective July 15, 1980; and ch. 295, sec. 61, effective July 15, 1980. -- Amended 1978 Ky. Acts ch. 384, sec. 68, effective June 17, 1978. -- Amended 1974 Ky. Acts ch. 200, sec. 1 -- Created 1956 Ky. Acts ch. 218, sec. 13, effective July 1, 1956. </history><metadata><effective>July 15, 1980</effective><lrc-note>.  This section was amended by two 1980 acts which do not appear to be in conflict and have been compiled together. </lrc-note><pdf-author>ganesan_m</pdf-author><pdf-creation-date>2015-07-02</pdf-creation-date><pdf-download-date>2016-03-18 12:16:37</pdf-download-date><original-link>http://www.lrc.ky.gov/statutes/statute.aspx?id=9398</original-link></metadata><tags><tag>computer-parsed</tag><tag>unverified</tag></tags></law>