<?xml version="1.0" encoding="UTF-8"?><law><structure><unit label="title" identifier="XXXIII" order_by="33">ADMINISTRATION OF TRUSTS AND ESTATES</unit><unit label="chapter" identifier="388" order_by="388">UNIFORM VETERANS' GUARDIANSHIP ACT </unit></structure><section_number>388.150</section_number><catch_line>388.150 repealed</catch_line><order_by>150</order_by><text>Repealed,1942.</text><history>Repealed 1942 Ky. Acts ch. 25, sec. 23. -- Recodified 1942 Ky. Acts ch. 208, sec. 1, effective October 1, 1942, from Ky. Stat. sec. 2043-15. </history><metadata><catchline-at-repeal>Commitment of veteran to U.S. Veterans' Hospital.</catchline-at-repeal><pdf-author>ganesan_m</pdf-author><pdf-creation-date>2015-07-02</pdf-creation-date><pdf-download-date>2016-03-18 12:15:33</pdf-download-date><original-link>http://www.lrc.ky.gov/statutes/statute.aspx?id=36086</original-link></metadata><tags><tag>computer-parsed</tag><tag>unverified</tag></tags></law>