<?xml version="1.0" encoding="UTF-8"?><law><structure><unit label="title" identifier="XV" order_by="15">ROADS, WATERWAYS, AND AVIATION</unit><unit label="chapter" identifier="177" order_by="177">STATE AND FEDERAL HIGHWAYS -- LIMITED ACCESS FACILITIES -- TURNPIKES -- ROAD BONDS -- BILLBOARDS -- RECYCLERS </unit></structure><section_number>177.370</section_number><catch_line>177.370 repealed</catch_line><order_by>370</order_by><text>Repealed, 1956. </text><history>  Repealed 1956 (2nd Extra Sess.) Ky. Acts ch. 4, sec. 4, effective June 26, 1956. -- Created 1948 Ky. Acts ch. 46, sec. 1. </history><metadata><catchline-at-repeal>  Recommendations and reports to General Assembly. </catchline-at-repeal><pdf-author>ganesan_m</pdf-author><pdf-creation-date>2015-07-02</pdf-creation-date><pdf-download-date>2016-03-18 12:16:50</pdf-download-date><original-link>http://www.lrc.ky.gov/statutes/statute.aspx?id=5318</original-link></metadata><tags><tag>computer-parsed</tag><tag>unverified</tag></tags></law>