<?xml version="1.0" encoding="UTF-8"?><law><structure><unit label="title" identifier="XII" order_by="12">CONSERVATION AND STATE DEVELOPMENT</unit><unit label="chapter" identifier="152" order_by="152">A ENERGY </unit></structure><section_number>152A.230</section_number><catch_line>152A.230 repealed</catch_line><order_by>230</order_by><text>Repealed, reenacted, and amended as KRS 11.340, effective 1990. </text><history>None supplied</history><metadata><former-codification> KRS 152.330. </former-codification><pdf-author>ganesan_m</pdf-author><pdf-creation-date>2015-07-01</pdf-creation-date><pdf-download-date>2016-03-18 12:16:58</pdf-download-date><original-link>http://www.lrc.ky.gov/statutes/statute.aspx?id=2408</original-link></metadata><tags><tag>computer-parsed</tag><tag>unverified</tag></tags></law>