<?xml version="1.0" encoding="UTF-8"?><law><structure><unit label="title" identifier="XIV" order_by="14">LIBRARIES AND ARCHIVES</unit><unit label="chapter" identifier="173" order_by="173">CITY, COUNTY, AND REGIONAL LIBRARIES </unit></structure><section_number>173.780</section_number><catch_line>173.780 repealed</catch_line><order_by>780</order_by><text>Repealed, 1982. </text><history>Repealed 1982 Ky. Acts ch. 245, sec. 18, effective July 15, 1982. -- Created 1964 Ky. Acts ch. 92, sec. 15. </history><metadata><catchline-at-repeal>  Attendance of librarians at meetings. </catchline-at-repeal><pdf-author>ganesan_m</pdf-author><pdf-creation-date>2015-07-02</pdf-creation-date><pdf-download-date>2016-03-18 12:16:47</pdf-download-date><original-link>http://www.lrc.ky.gov/statutes/statute.aspx?id=4983</original-link></metadata><tags><tag>computer-parsed</tag><tag>unverified</tag></tags></law>