<?xml version="1.0" encoding="UTF-8"?><law><structure><unit label="title" identifier="XXIX" order_by="29">COMMERCE AND TRADE</unit><unit label="chapter" identifier="369" order_by="369">INFORMATION TECHNOLOGY </unit></structure><section_number>369.101</section_number><catch_line>Short title for KRS 369.101 to 369.120. </catch_line><order_by>101</order_by><text>KRS 369.101 to 369.120 may be cited as the Uniform Electronic Transactions Act. </text><history> Created 2000 Ky. Acts ch. 301, sec. 1, effective August 1, 2000. </history><metadata><effective> August 1, 2000 </effective><pdf-author>ganesan_m</pdf-author><pdf-creation-date>2015-07-02</pdf-creation-date><pdf-download-date>2016-03-18 12:15:41</pdf-download-date><original-link>http://www.lrc.ky.gov/statutes/statute.aspx?id=35200</original-link></metadata><tags><tag>computer-parsed</tag><tag>unverified</tag></tags></law>