<?xml version="1.0" encoding="UTF-8"?><law><structure><unit label="title" identifier="II" order_by="2">LEGISLATIVE BRANCH</unit><unit label="chapter" identifier="7" order_by="7">A PLANNING AND OVERSIGHT OF GOVERNMENTAL FINANCE </unit></structure><section_number>7A.200</section_number><catch_line>Public Pension Oversight Board.     </catch_line><order_by>200</order_by><text>The Public Pension Oversight Board of the Kentucky General Assembly is hereby established. The purpose of the board shall be to review, analyze, and provide oversight to the General Assembly on the benefits, administration, investments, funding, laws and administrative regulations, and legislation pertaining to the state-administered retirement systems. </text><history> Amended 2015 Ky. Acts ch. 27, sec. 1, effective June 24, 2015. -- Created 2013 Ky. Acts ch. 120, sec. 1, effective July 1, 2013. </history><metadata><effective> June 24, 2015 </effective><pdf-author>ganesan_m</pdf-author><pdf-creation-date>2015-07-03</pdf-creation-date><pdf-download-date>2016-03-18 12:15:14</pdf-download-date><original-link>http://www.lrc.ky.gov/statutes/statute.aspx?id=44268</original-link></metadata><tags><tag>computer-parsed</tag><tag>unverified</tag></tags></law>