<?xml version="1.0" encoding="UTF-8"?><law><structure><unit label="title" identifier="XVI" order_by="16">MOTOR VEHICLES</unit><unit label="chapter" identifier="186" order_by="186">LICENSING OF MOTOR VEHICLES, OPERATORS, AND TRAILERS </unit></structure><section_number>186.665</section_number><catch_line>Inability to register trailer, semitrailer, mobile home or recreational vehicle before April 1. </catch_line><order_by>665</order_by><text>If an owner because of sickness or absence from the state is unable to renew the registration of his trailer, semitrailer, mobile home or recreational vehicle on or before April 1, he will be deemed to have complied with the law, if before operating the trailer, semitrailer, mobile home or recreational vehicle in this state he registers it at some later date and pays the fee for the full year, just as though he had renewed the registration on or before April 1. The owner shall file with the application an affidavit showing sickness or absence. </text><history>Amended 1982 Ky. Acts ch. 395, sec. 13, effective July 15, 1982. -- Amended 1966 Ky. Acts ch. 139, sec. 16, effective January 1, 1967. -- Created 1956 (2nd Extra. Sess.) Ky. Acts ch. 6, sec. 4. </history><metadata><effective>July 15, 1982 </effective><pdf-author>ganesan_m</pdf-author><pdf-creation-date>2015-07-02</pdf-creation-date><pdf-download-date>2016-03-18 12:16:45</pdf-download-date><original-link>http://www.lrc.ky.gov/statutes/statute.aspx?id=6108</original-link></metadata><tags><tag>computer-parsed</tag><tag>unverified</tag></tags></law>