<?xml version="1.0" encoding="UTF-8"?><law><structure><unit label="title" identifier="IV" order_by="4">JUDICIAL BRANCH</unit><unit label="chapter" identifier="27" order_by="27">A JUDICIAL SUPPORT AGENCIES AND PERSONNEL </unit></structure><section_number>27A.050</section_number><catch_line>Administrative Office of Courts -- Appointment of director -- Compensation -- Prohibition. </catch_line><order_by>050</order_by><text>The Administrative Office of the Courts is created to serve as the staff for the Chief Justice in executing the policies and programs of the Court of Justice. The director of the Administrative Office of the Courts, employees thereof, and administrative assistants of the Chief Justice shall serve at the pleasure of the Chief Justice. Provided, however, the director shall be appointed or reappointed at least every four (4) years with the advice and consent of the Senate; but if the Senate is not in session when a term expires or a vacancy occurs, the Chief Justice shall make the appointment to take effect at once, subject to the approval of the Senate when convened. The salaries of the director, employees thereof, and administrative assistants of the Chief Justice shall be fixed by order of the Chief Justice and paid monthly or at such other periods as may be consonant with the policy applicable to payment of salaries of state employees out of the State Treasury. While holding their positions the director, employees of the office and administrative assistants shall not practice law in any court of this Commonwealth. </text><history>Created 1976 (1st Extra. Sess.) Ky. Acts ch. 33, sec. 1. </history><metadata><pdf-author>ganesan_m</pdf-author><pdf-creation-date>2015-07-02</pdf-creation-date><pdf-download-date>2016-03-18 12:17:22</pdf-download-date><original-link>http://www.lrc.ky.gov/statutes/statute.aspx?id=20936</original-link></metadata><tags><tag>computer-parsed</tag><tag>unverified</tag></tags></law>