<?xml version="1.0" encoding="UTF-8"?><law><structure><unit label="title" identifier="XVIII" order_by="18">PUBLIC HEALTH</unit><unit label="chapter" identifier="216" order_by="216">HEALTH FACILITIES AND SERVICES </unit></structure><section_number>216.555</section_number><catch_line>Citation by cabinet for violations of regulations, standards, and requirements. </catch_line><order_by>555</order_by><text>If upon inspection or investigation the cabinet determines that a long-term care facility has violated the regulations, standards, and requirements as set forth by the cabinet pursuant to the provisions of KRS 216.510 to 216.525, or applicable federal laws and regulations governing the certification of a long-term care facility under Title 18 or 19 of the Social Security Act and such violation has been classified in KRS 216.557, the cabinet shall immediately issue a citation to the licensee of the long-term care facility. Each notice of violation shall be prepared in writing and shall specify the nature of the violation, and the statutory provision or regulation alleged to have been violated. </text><history> Amended 1998 Ky. Acts ch. 189, sec. 5, effective July 15, 1998. -- Created 1982 Ky. Acts ch. 157, sec. 9, effective July 15, 1982. </history><metadata><effective> July 15, 1998 </effective><pdf-author>ganesan_m</pdf-author><pdf-creation-date>2015-07-02</pdf-creation-date><pdf-download-date>2016-03-18 12:16:38</pdf-download-date><original-link>http://www.lrc.ky.gov/statutes/statute.aspx?id=9077</original-link></metadata><tags><tag>computer-parsed</tag><tag>unverified</tag></tags></law>