<?xml version="1.0" encoding="UTF-8"?><law><structure><unit label="title" identifier="XXXV" order_by="35">DOMESTIC RELATIONS</unit><unit label="chapter" identifier="404" order_by="404">CONTRACTS AND SEPARATE ESTATE OF MARRIED WOMEN </unit></structure><section_number>404.050</section_number><catch_line>When wife may convey or mortgage her real estate free from husband's claim. </catch_line><order_by>050</order_by><text>When a husband has been adjudged mentally disabled by a court of competent jurisdiction, the wife, by judgment of a court of equity, may be empowered to sell and convey by her own deed, or to mortgage by appropriate instrument, any of her real estate freed as to it and its proceeds from any claim of her husband. </text><history>Amended 1982 Ky. Acts ch. 141, sec. 128, effective July 1, 1982. -- Amended 1978 Ky. Acts ch. 92, sec. 14, effective June 17, 1978. -- Amended 1942 Ky. Acts ch. 152, secs. 1 and 3. -- Recodified 1942 Ky. Acts ch. 208, sec. 1, effective October 1, 1942, from Ky. Stat. sec. 2131. </history><metadata><effective>July 1, 1982</effective><note>1980 Ky. Acts ch. 396, sec. 139 would have amended this section effective July 1, 1982. However, 1980 Ky. Acts ch. 396 was repealed by 1982 Ky. Acts ch. 141, sec. 146, also effective July 1, 1982. </note><pdf-author>ganesan_m</pdf-author><pdf-creation-date>2015-07-02</pdf-creation-date><pdf-download-date>2016-03-18 12:15:31</pdf-download-date><original-link>http://www.lrc.ky.gov/statutes/statute.aspx?id=17539</original-link></metadata><tags><tag>computer-parsed</tag><tag>unverified</tag></tags></law>