<?xml version="1.0" encoding="UTF-8"?><law><structure><unit label="title" identifier="XXI" order_by="21">AGRICULTURE AND ANIMALS</unit><unit label="chapter" identifier="262" order_by="262">SOIL AND WATER CONSERVATION </unit></structure><section_number>262.210</section_number><catch_line>Nomination of supervisors by petition. </catch_line><order_by>210</order_by><text>Nominating petitions shall be filed with the clerk of the county in which the district lies to nominate candidates for supervisors of the district. Such petitions shall be filed by at least the last date prescribed by the election law generally for filing certificates of nomination prior to a general election. Such petitions shall be filed no later than 4 p.m. local time at the place of filing when filed on the last date on which such papers are permitted to be filed. Each nominating petition shall be subscribed by twenty-five (25) or more qualified voters who are residents of the territory to be encompassed by the district. Resident qualified voters may join in nominating by petition more than one (1) candidate for supervisor. The nominating petition shall state the residence and post office address of each candidate, that he is legally qualified to hold the office, and that the subscribers desire, and are legally qualified, to vote for the candidate. The county clerk shall certify the nomination and election of supervisors to the commission. </text><history>Amended 1986 Ky. Acts ch. 185, sec. 5, effective January 1, 1987; ch. 470, sec. 42, effective July 15, 1986. -- Amended 1984 Ky. Acts ch. 185, sec. 29, effective July 13, 1984. -- Amended 1974 Ky. Acts ch. 151, sec. 4. -- Recodified 1942 Ky. Acts ch. 208, sec. 1, effective October 1, 1942, from Ky. Stat. sec. 42i-6. </history><metadata><effective>January 1, 1987</effective><lrc-note>.This section was amended by two 1986 Acts which do not appear to be in conflict and have been compiled together. </lrc-note><pdf-author>ganesan_m</pdf-author><pdf-creation-date>2015-07-02</pdf-creation-date><pdf-download-date>2016-03-18 12:16:26</pdf-download-date><original-link>http://www.lrc.ky.gov/statutes/statute.aspx?id=12730</original-link></metadata><tags><tag>computer-parsed</tag><tag>unverified</tag></tags></law>