<?xml version="1.0" encoding="UTF-8"?><law><structure><unit label="title" identifier="XXIX" order_by="29">COMMERCE AND TRADE</unit><unit label="chapter" identifier="" order_by=""></unit></structure><section_number>362.1-117</section_number><catch_line>Registered office -- Registered agent.   </catch_line><order_by>1-117</order_by><text>Each limited liability partnership and each foreign limited liability partnership authorized to transact business in the Commonwealth shall continuously maintain in this Commonwealth a registered office and a registered agent that comply with KRS 14A.4-010. </text><history> Repealed, reenacted, and amended 2010 Ky. Acts ch. 151, sec. 95, effective January 1, 2011. -- Created 2006 Ky. Acts ch. 149, sec. 17, effective July 12, 2006. </history><metadata><effective> January 1, 2011 </effective><pdf-author>ganesan_m</pdf-author><pdf-creation-date>2015-07-02</pdf-creation-date><pdf-download-date>2016-03-18 12:15:44</pdf-download-date><original-link>http://www.lrc.ky.gov/statutes/statute.aspx?id=36771</original-link></metadata><tags><tag>computer-parsed</tag><tag>unverified</tag></tags></law>