<?xml version="1.0" encoding="UTF-8"?><law><structure><unit label="title" identifier="XVI" order_by="16">MOTOR VEHICLES</unit><unit label="chapter" identifier="186" order_by="186">LICENSING OF MOTOR VEHICLES, OPERATORS, AND TRAILERS </unit></structure><section_number>186.245</section_number><catch_line>Posting of notice about 2006 increases in fees of county clerks. </catch_line><order_by>245</order_by><text>Beginning January 1, 2007, every county clerk shall post a permanent notice that the fee increases contained in 2006 Ky. Acts ch. 255 were requested by the Kentucky County Clerks Association. The notice shall be printed in bold face type of sufficient point size to be read from a distance of at least three (3) feet. The notice shall be posted in a conspicuous place to ensure that every person who enters the county clerk's office will readily see the notice. </text><history> Amended 2006 Ky. Acts ch. 255, sec. 2, effective January 1, 2007. -- Created 1994 Ky. Acts ch. 428, sec. 36, effective July 15, 1994. </history><metadata><effective> January 1, 2007 </effective><pdf-author>ganesan_m</pdf-author><pdf-creation-date>2015-07-02</pdf-creation-date><pdf-download-date>2016-03-18 12:16:45</pdf-download-date><original-link>http://www.lrc.ky.gov/statutes/statute.aspx?id=6030</original-link></metadata><tags><tag>computer-parsed</tag><tag>unverified</tag></tags></law>