<?xml version="1.0" encoding="UTF-8"?><law><structure><unit label="title" identifier="XXXVIII" order_by="38">WITNESSES, EVIDENCE, NOTARIES, COMMISSIONERS</unit><unit label="chapter" identifier="422" order_by="422">EVIDENCE AND LOST RECORDS </unit></structure><section_number>422.230</section_number><catch_line>Order of court or bond filed therein -- How supplied when lost. </catch_line><order_by>230</order_by><text>If an order of a court, appointing an administrator, guardian or any person to any place, station, or trust or, if the bond executed by any such person, or by an officer, is destroyed, obliterated, or lost, the court shall, by the appropriate proceeding, due notice thereof being given, supply the record, and require such person to execute a new bond, with good and sufficient sureties. If the person fails to execute a new bond when so required the court shall enter an order vacating his office or station. </text><history>Amended 1976 (1st Extra. Sess.) Ky. Acts ch. 14, sec. 426, effective January 2, 1978. -- Recodified 1942 Ky. Acts ch. 208, sec. 1, effective October 1, 1942, from Ky. Stat. sec. 3993. </history><metadata><effective>January 2, 1978</effective><pdf-author>ganesan_m</pdf-author><pdf-creation-date>2015-07-02</pdf-creation-date><pdf-download-date>2016-03-18 12:15:34</pdf-download-date><original-link>http://www.lrc.ky.gov/statutes/statute.aspx?id=18131</original-link></metadata><tags><tag>computer-parsed</tag><tag>unverified</tag></tags></law>