<?xml version="1.0" encoding="UTF-8"?><law><structure><unit label="title" identifier="XVIII" order_by="18">PUBLIC HEALTH</unit><unit label="chapter" identifier="219" order_by="219">HOTEL, FOOD SERVICE, AND MOBILE HOME AND RECREATIONAL VEHICLE PARK REGULATIONS </unit></structure><section_number>219.350</section_number><catch_line>Permit for construction of community. </catch_line><order_by>350</order_by><text>No community shall be constructed or altered without a permit as provided in KRS 219.310 to 219.410. An application for a permit to construct or alter a community shall be made to the cabinet upon forms provided by it. The application shall include plans for construction or alteration of the community and shall contain such information in regard to the proposed community as the cabinet may reasonably require, which may include affirmative evidence of ability to comply with requirements of KRS 219.310 to 219.410 and regulations adopted by the secretary. All plans for the construction, installation, or alteration of buildings shall be forwarded by the cabinet to the Department of Housing, Buildings and Construction. Only the Department of Housing, Buildings and Construction shall review such plans for conformance with the Uniform State Building Code. The Department of Housing, Buildings and Construction shall expedite the review of such plans and return them to the Cabinet for Health and Family Services for completion of the application process. Each application for a permit to construct or alter a community shall be accompanied by a permit fee of forty-seven dollars ($47). The cabinet may, by administrative regulation, increase this fee by no more than five percent (5%) per year, not to exceed a maximum fee of seventy dollars ($70). Each permit to construct shall be issued only for the person and premises, including the number of spaces named in the application and shall not be transferable. Each permit to construct shall expire one <section prefix="1">year from date of issuance. </section></text><history> Amended 2010 Ky. Acts ch. 24, sec. 327, effective July 15, 2010. -- Amended 2005 Ky. Acts ch. 99, sec. 555, effective June 20, 2005. -- Amended 2002 Ky. Acts ch. 242, sec. 5, effective July 15, 2002. -- Amended 1998 Ky. Acts ch. 426, sec. 495, effective July 15, 1998. -- Amended 1978 Ky. Acts ch. 117, sec. 35, effective February 28, 1980. -- Amended 1974 Ky. Acts ch. 74, Art. VI, sec. 107(22). -- Created 1972 Ky. Acts ch. 281, sec. 5. </history><metadata><effective> July 15, 2010 </effective><pdf-author>ganesan_m</pdf-author><pdf-creation-date>2015-07-02</pdf-creation-date><pdf-download-date>2016-03-18 12:16:35</pdf-download-date><original-link>http://www.lrc.ky.gov/statutes/statute.aspx?id=9758</original-link></metadata><tags><tag>computer-parsed</tag><tag>unverified</tag></tags></law>