<?xml version="1.0" encoding="UTF-8"?><law><structure><unit label="title" identifier="XII" order_by="12">CONSERVATION AND STATE DEVELOPMENT</unit><unit label="chapter" identifier="146" order_by="146">NATURAL RESOURCES </unit></structure><section_number>146.660</section_number><catch_line>Administrative mission units of museum -- Associate directors. </catch_line><order_by>660</order_by><text>The purposes of KRS 146.650 to 146.666 shall be carried out through the operation of mission units. When the Kentucky Natural History Museum is established, the mission units shall become administrative units of the museum. Each unit shall be managed by an associate director. </text><history> Created 2000 Ky. Acts ch. 329, sec. 6, effective July 14, 2000. </history><metadata><effective> July 14, 2000 </effective><pdf-author>ganesan_m</pdf-author><pdf-creation-date>2015-07-01</pdf-creation-date><pdf-download-date>2016-03-18 12:16:59</pdf-download-date><original-link>http://www.lrc.ky.gov/statutes/statute.aspx?id=1553</original-link></metadata><tags><tag>computer-parsed</tag><tag>unverified</tag></tags></law>