<?xml version="1.0" encoding="UTF-8"?><law><structure><unit label="title" identifier="XXVII" order_by="27">LABOR AND HUMAN RIGHTS</unit><unit label="chapter" identifier="337" order_by="337">WAGES AND HOURS </unit></structure><section_number>337.340</section_number><catch_line>Power to question employees. </catch_line><order_by>340</order_by><text>Every employer shall permit the commissioner or the commissioner's authorized agent to question any of his or her employees in the place of employment and during work hours in respect to the wages paid to and the hours worked by such employee or other employees. </text><history> Amended 2010 Ky. Acts ch. 24, sec. 1733, effective July 15, 2010. -- Recodified 1942 Ky. Acts ch. 208, sec. 1, effective October 1, 1942, from Ky. Stat. sec. 4767a-15. </history><metadata><effective> July 15, 2010 </effective><pdf-author>ganesan_m</pdf-author><pdf-creation-date>2015-07-02</pdf-creation-date><pdf-download-date>2016-03-18 12:15:49</pdf-download-date><original-link>http://www.lrc.ky.gov/statutes/statute.aspx?id=32074</original-link></metadata><tags><tag>computer-parsed</tag><tag>unverified</tag></tags></law>