<?xml version="1.0" encoding="UTF-8"?><law><structure><unit label="title" identifier="II" order_by="2">LEGISLATIVE BRANCH</unit><unit label="chapter" identifier="5" order_by="5">LEGISLATIVE DISTRICTS </unit></structure><section_number>5.231</section_number><catch_line>Thirty-first Representative District. </catch_line><order_by>231</order_by><text>The Thirty-first Representative District shall consist of the following territory: 
    ---CENSUS--- 
COUNTY PREC NAME  TRACT BLK SECT 
JEFFERSON D101 PRECINCT 101 31 DISTRICT 010500 2000 
JEFFERSON D101 PRECINCT 101 31 DISTRICT 010500 2001 
JEFFERSON D101 PRECINCT 101 31 DISTRICT 010500 2002 
JEFFERSON D101 PRECINCT 101 31 DISTRICT 010500 2003 
JEFFERSON D101 PRECINCT 101 31 DISTRICT 010500 2023 
JEFFERSON D101 PRECINCT 101 31 DISTRICT 010500 2024 
JEFFERSON D101 PRECINCT 101 31 DISTRICT 010500 2025 
JEFFERSON D101 PRECINCT 101 31 DISTRICT 010500 2032 
JEFFERSON D101 PRECINCT 101 31 DISTRICT 010500 2034 
JEFFERSON D101 PRECINCT 101 31 DISTRICT 010500 2035 
JEFFERSON D101 PRECINCT 101 31 DISTRICT 010500 2038 
JEFFERSON D101 PRECINCT 101 31 DISTRICT 010500 2040 
JEFFERSON D101 PRECINCT 101 31 DISTRICT 010500 2041 
JEFFERSON D101 PRECINCT 101 31 DISTRICT 010500 2042 
JEFFERSON D101 PRECINCT 101 31 DISTRICT 010500 2043 
JEFFERSON D101 PRECINCT 101 31 DISTRICT 010500 2044 
JEFFERSON D101 PRECINCT 101 31 DISTRICT 010500 2046 0202 
JEFFERSON D101 PRECINCT 101 31 DISTRICT 010500 2047 
JEFFERSON D101 PRECINCT 101 31 DISTRICT 010500 2049 
JEFFERSON D101 PRECINCT 101 31 DISTRICT 010500 2050 0102 
JEFFERSON D101 PRECINCT 101 31 DISTRICT 010601 1014 
JEFFERSON D101 PRECINCT 101 31 DISTRICT 010601 1016 
JEFFERSON D101 PRECINCT 101 31 DISTRICT 010601 1017 
JEFFERSON D101 PRECINCT 101 31 DISTRICT 010601 1018 
JEFFERSON D101 PRECINCT 101 31 DISTRICT 010601 1019 
JEFFERSON D101 PRECINCT 101 31 DISTRICT 010601 1020 
JEFFERSON D101 PRECINCT 101 31 DISTRICT 010601 1021 
JEFFERSON D101 PRECINCT 101 31 DISTRICT 010601 1022 
JEFFERSON D101 PRECINCT 101 31 DISTRICT 010601 1023 
JEFFERSON D101 PRECINCT 101 31 DISTRICT 010601 1024 
JEFFERSON D101 PRECINCT 101 31 DISTRICT 010601 1025 
JEFFERSON D101 PRECINCT 101 31 DISTRICT 010601 1026 
JEFFERSON D101 PRECINCT 101 31 DISTRICT 010601 1027 
JEFFERSON D101 PRECINCT 101 31 DISTRICT 010601 1028 
JEFFERSON D101 PRECINCT 101 31 DISTRICT 010601 1029 
JEFFERSON D101 PRECINCT 101 31 DISTRICT 010601 1030 
JEFFERSON D101 PRECINCT 101 31 DISTRICT 010601 1036 
JEFFERSON D101 PRECINCT 101 31 DISTRICT 010800 2000 
JEFFERSON D101 PRECINCT 101 31 DISTRICT 010800 2001 
JEFFERSON D104 PRECINCT 104 31 DISTRICT 
JEFFERSON D106 PRECINCT 106 31 DISTRICT 
JEFFERSON D108 PRECINCT 108 31 DISTRICT 
JEFFERSON D109 PRECINCT 109 31 DISTRICT 
JEFFERSON D110 PRECINCT 110 31 DISTRICT 
JEFFERSON D113 PRECINCT 113 31 DISTRICT 011114 1000 
JEFFERSON D113 PRECINCT 113 31 DISTRICT 011114 1001 
JEFFERSON D113 PRECINCT 113 31 DISTRICT 011114 1002 0102 
JEFFERSON D113 PRECINCT 113 31 DISTRICT 011114 1003 0202 
JEFFERSON D113 PRECINCT 113 31 DISTRICT 011114 1004 
JEFFERSON D113 PRECINCT 113 31 DISTRICT 011114 1005 
JEFFERSON D113 PRECINCT 113 31 DISTRICT 011114 1006 
JEFFERSON D113 PRECINCT 113 31 DISTRICT 011114 2003 0202 
JEFFERSON D113 PRECINCT 113 31 DISTRICT 011114 2004 
JEFFERSON D113 PRECINCT 113 31 DISTRICT 011114 2005 
JEFFERSON D113 PRECINCT 113 31 DISTRICT 011114 2006 0102 
JEFFERSON D113 PRECINCT 113 31 DISTRICT 011114 2007 
JEFFERSON D113 PRECINCT 113 31 DISTRICT 011114 2008 
JEFFERSON D113 PRECINCT 113 31 DISTRICT 011114 2009 0102 
JEFFERSON D113 PRECINCT 113 31 DISTRICT 011114 2010 0102 
JEFFERSON D113 PRECINCT 113 31 DISTRICT 011114 2012 0202 
JEFFERSON D114 PRECINCT 114 31 DISTRICT 
JEFFERSON D115 PRECINCT 115 31 DISTRICT 
JEFFERSON D116 PRECINCT 116 31 DISTRICT 
JEFFERSON D117 PRECINCT 117 31 DISTRICT 
JEFFERSON D120 PRECINCT 120 31 DISTRICT 
JEFFERSON D121 PRECINCT 121 31 DISTRICT 
JEFFERSON D122 PRECINCT 122 31 DISTRICT 
JEFFERSON D126 PRECINCT 126 31 DISTRICT 
JEFFERSON D129 PRECINCT 129 31 DISTRICT 
JEFFERSON D130 PRECINCT 130 31 DISTRICT 010901 1000 
JEFFERSON D130 PRECINCT 130 31 DISTRICT 010902 1007 0202 
JEFFERSON D130 PRECINCT 130 31 DISTRICT 010902 1008 
JEFFERSON D130 PRECINCT 130 31 DISTRICT 010902 1012 
JEFFERSON D130 PRECINCT 130 31 DISTRICT 010902 1013 
JEFFERSON D130 PRECINCT 130 31 DISTRICT 010902 1016 
JEFFERSON D130 PRECINCT 130 31 DISTRICT 010902 1017 
JEFFERSON D130 PRECINCT 130 31 DISTRICT 010902 1020 
JEFFERSON D130 PRECINCT 130 31 DISTRICT 010902 1021 
JEFFERSON D130 PRECINCT 130 31 DISTRICT 010902 1022 
JEFFERSON D130 PRECINCT 130 31 DISTRICT 010902 1023 
JEFFERSON D130 PRECINCT 130 31 DISTRICT 010902 1024 
JEFFERSON D130 PRECINCT 130 31 DISTRICT 010902 1025 
JEFFERSON D130 PRECINCT 130 31 DISTRICT 010902 2000 
JEFFERSON D130 PRECINCT 130 31 DISTRICT 010902 2002 
JEFFERSON D130 PRECINCT 130 31 DISTRICT 010902 2004 
JEFFERSON D131 PRECINCT 131 31 DISTRICT 
JEFFERSON D132 PRECINCT 132 31 DISTRICT 
JEFFERSON D135 PRECINCT 135 31 DISTRICT 
JEFFERSON D136 PRECINCT 136 31 DISTRICT 011114 2000 
JEFFERSON D136 PRECINCT 136 31 DISTRICT 011114 2001 
JEFFERSON D136 PRECINCT 136 31 DISTRICT 011114 2002 
JEFFERSON D136 PRECINCT 136 31 DISTRICT 011114 2003 0102 
JEFFERSON D136 PRECINCT 136 31 DISTRICT 011114 2006 0202 
JEFFERSON D136 PRECINCT 136 31 DISTRICT 011114 2012 0102 
JEFFERSON D136 PRECINCT 136 31 DISTRICT 011114 2013 
JEFFERSON D136 PRECINCT 136 31 DISTRICT 011114 2014 
JEFFERSON D136 PRECINCT 136 31 DISTRICT 011114 2015 
JEFFERSON D136 PRECINCT 136 31 DISTRICT 011114 3000 
JEFFERSON D136 PRECINCT 136 31 DISTRICT 011114 3001 
JEFFERSON D136 PRECINCT 136 31 DISTRICT 011114 3002 
JEFFERSON D136 PRECINCT 136 31 DISTRICT 011114 3003 
JEFFERSON D136 PRECINCT 136 31 DISTRICT 011114 3004 
JEFFERSON D136 PRECINCT 136 31 DISTRICT 011114 3009 
JEFFERSON D136 PRECINCT 136 31 DISTRICT 011114 3010 
JEFFERSON D137 PRECINCT 137 31 DISTRICT 011110 1011 
JEFFERSON D137 PRECINCT 137 31 DISTRICT 011110 1012 
JEFFERSON D137 PRECINCT 137 31 DISTRICT 011110 1030 
JEFFERSON D137 PRECINCT 137 31 DISTRICT 011110 1031 
JEFFERSON D137 PRECINCT 137 31 DISTRICT 011110 1032 
JEFFERSON D137 PRECINCT 137 31 DISTRICT 011110 1033 
JEFFERSON D137 PRECINCT 137 31 DISTRICT 011110 1034 
JEFFERSON D137 PRECINCT 137 31 DISTRICT 011110 1035 
JEFFERSON D137 PRECINCT 137 31 DISTRICT 011110 2002 
JEFFERSON D137 PRECINCT 137 31 DISTRICT 011110 2003 
JEFFERSON D137 PRECINCT 137 31 DISTRICT 011110 2005 
JEFFERSON D137 PRECINCT 137 31 DISTRICT 011110 3002 
JEFFERSON D137 PRECINCT 137 31 DISTRICT 011110 3003 
JEFFERSON D137 PRECINCT 137 31 DISTRICT 011110 3004 
JEFFERSON D137 PRECINCT 137 31 DISTRICT 011110 3005 
JEFFERSON D137 PRECINCT 137 31 DISTRICT 011110 3006 
JEFFERSON D137 PRECINCT 137 31 DISTRICT 011110 3008 
JEFFERSON D137 PRECINCT 137 31 DISTRICT 011110 3009 
JEFFERSON D137 PRECINCT 137 31 DISTRICT 011110 3013 
JEFFERSON D138 PRECINCT 138 31 DISTRICT 
JEFFERSON D139 PRECINCT 139 31 DISTRICT 
JEFFERSON D140 PRECINCT 140 31 DISTRICT 
JEFFERSON D141 PRECINCT 141 31 DISTRICT 
JEFFERSON D142 PRECINCT 142 31 DISTRICT 
JEFFERSON D143 PRECINCT 143 31 DISTRICT 011110 1006 
JEFFERSON D143 PRECINCT 143 31 DISTRICT 011110 1007 
JEFFERSON D143 PRECINCT 143 31 DISTRICT 011110 1009 
JEFFERSON D143 PRECINCT 143 31 DISTRICT 011110 1010 </text><history> Repealed and reenacted 2013 (1st Extra. Sess.) Ky. Acts ch. 1, sec. 69, effective August 23, 2013. -- Repealed and reenacted 2002 Ky. Acts ch. 1, sec. 31, effective January 31, 2002. -- Repealed and reenacted 1996 Ky. Acts ch. 1, sec. 31, effective January 11, 1996. -- Created 1991 (2d Extra. Sess.) Ky. Acts ch. 5, sec. 31, effective January 8, 1992. </history><metadata><effective> August 23, 2013 </effective><pdf-author>ganesan_m</pdf-author><pdf-creation-date>2015-07-02</pdf-creation-date><pdf-download-date>2016-03-18 12:15:14</pdf-download-date><original-link>http://www.lrc.ky.gov/statutes/statute.aspx?id=42821</original-link></metadata><tags><tag>computer-parsed</tag><tag>unverified</tag></tags></law>