<?xml version="1.0" encoding="UTF-8"?><law><structure><unit label="title" identifier="XV" order_by="15">ROADS, WATERWAYS, AND AVIATION</unit><unit label="chapter" identifier="183" order_by="183">AVIATION </unit></structure><section_number>183.769</section_number><catch_line>Compliance with laws and regulations. </catch_line><order_by>769</order_by><text>Whenever state funds are used or sought to be used, all governmental units in this state, whether acting alone or jointly with another governmental unit or with the United States government or with the state, shall comply with the terms of KRS 183.763 to 183.772 and all rules and regulations adopted thereunder, and secure the approval of the cabinet. </text><history>Amended 1964 Ky. Acts ch. 134, sec. 20. -- Amended 1960 Ky. Acts ch. 179, sec. 73. -- Created 1948 Ky. Acts ch. 239, sec. 10. </history><metadata><pdf-author>ganesan_m</pdf-author><pdf-creation-date>2015-07-02</pdf-creation-date><pdf-download-date>2016-03-18 12:16:46</pdf-download-date><original-link>http://www.lrc.ky.gov/statutes/statute.aspx?id=5836</original-link></metadata><tags><tag>computer-parsed</tag><tag>unverified</tag></tags></law>