<?xml version="1.0" encoding="UTF-8"?><law><structure><unit label="title" identifier="XVI" order_by="16">MOTOR VEHICLES</unit><unit label="chapter" identifier="189" order_by="189">TRAFFIC REGULATIONS -- VEHICLE EQUIPMENT AND STORAGE </unit></structure><section_number>189.393</section_number><catch_line>Complying with traffic officer's signal. </catch_line><order_by>393</order_by><text>No operator of a vehicle, after having received a visual or audible signal from an officer directing traffic shall knowingly or wantonly disregard the signal so as to interfere with or endanger the operation of the traffic officer or other vehicles or pedestrians. </text><history> Amended 1998 Ky. Acts ch. 606, sec. 160, effective July 15, 1998. -- Created 1972 Ky. Acts ch. 128, sec. 1 </history><metadata><effective> July 15, 1998 </effective><pdf-author>ganesan_m</pdf-author><pdf-creation-date>2015-07-02</pdf-creation-date><pdf-download-date>2016-03-18 12:16:44</pdf-download-date><original-link>http://www.lrc.ky.gov/statutes/statute.aspx?id=6386</original-link></metadata><tags><tag>computer-parsed</tag><tag>unverified</tag></tags></law>