<?xml version="1.0" encoding="UTF-8"?><law><structure><unit label="title" identifier="XXV" order_by="25">BUSINESS AND FINANCIAL INSTITUTIONS</unit><unit label="chapter" identifier="303" order_by="303">BURIAL ASSOCIATIONS </unit></structure><section_number>303.010</section_number><catch_line>303.010 repealed</catch_line><order_by>010</order_by><text>Repealed, 1970. </text><history>Repealed 1970 Ky. Acts ch. 301, subtit. 99, sec. 3, effective June 18, 1970. -- Amended 1968 Ky. Acts ch. 147, sec. 1, effective June 13, 1968. -- Amended 1966 Ky. Acts ch. 255, sec. 240, effective June 16, 1966. -- Amended 1950 ch. 118, sec. 1, effective June 15, 1950. -- Amended 1946 Ky. Acts ch. 51, secs. 1, 2, 3, and 5. -- Recodified 1942 Ky. Acts ch. 208, sec. 1, effective October 1, 1942, from Ky. Stat. secs. 199a-10, 199a-19, 2089L-3. </history><metadata><catchline-at-repeal>  Construction of chapter.</catchline-at-repeal><pdf-author>ganesan_m</pdf-author><pdf-creation-date>2015-07-02</pdf-creation-date><pdf-download-date>2016-03-18 12:16:09</pdf-download-date><original-link>http://www.lrc.ky.gov/statutes/statute.aspx?id=16000</original-link></metadata><tags><tag>computer-parsed</tag><tag>unverified</tag></tags></law>