<?xml version="1.0" encoding="UTF-8"?><law><structure><unit label="title" identifier="XV" order_by="15">ROADS, WATERWAYS, AND AVIATION</unit><unit label="chapter" identifier="176" order_by="176">DEPARTMENT OF HIGHWAYS </unit></structure><section_number>176.057</section_number><catch_line>Certain railroad property to be considered roads -- Use of funds for maintenance and repair. </catch_line><order_by>057</order_by><text>For the purposes of this chapter and KRS Chapter 178 on and after July 1, 2010, railroad crossings, railroad spurs that access industrial parks, and shortline railroads at or near intersections with roadways shall be considered roads. The industrial access road fund within the Transportation Cabinet and other funds specified by the secretary or requested by the secretary of the Cabinet for Economic Development may be used for their maintenance and repair. </text><history> Created 2009 (1st Extra. Sess.) Ky. Acts ch. 1, sec. 54, effective June 26, 2009. </history><metadata><effective> June 26, 2009 </effective><pdf-author>ganesan_m</pdf-author><pdf-creation-date>2015-07-02</pdf-creation-date><pdf-download-date>2016-03-18 12:16:46</pdf-download-date><original-link>http://www.lrc.ky.gov/statutes/statute.aspx?id=5167</original-link></metadata><tags><tag>computer-parsed</tag><tag>unverified</tag></tags></law>