<?xml version="1.0" encoding="UTF-8"?><law><structure><unit label="title" identifier="XII" order_by="12">CONSERVATION AND STATE DEVELOPMENT</unit><unit label="chapter" identifier="152" order_by="152">ENERGY DEVELOPMENT </unit></structure><section_number>152.570</section_number><catch_line>152.570 repealed</catch_line><order_by>570</order_by><text>Repealed, 1976. </text><history>Repealed 1976 Ky. Acts ch. 299, sec. 91. -- Amended 1966 Ky. Acts ch. 220, sec. 11 -- Created 1962 Ky. Acts ch. 100, sec. 7. </history><metadata><catchline-at-repeal>  Commissioner of health to be health and safety officer. </catchline-at-repeal><pdf-author>ganesan_m</pdf-author><pdf-creation-date>2015-07-01</pdf-creation-date><pdf-download-date>2016-03-18 12:16:57</pdf-download-date><original-link>http://www.lrc.ky.gov/statutes/statute.aspx?id=2329</original-link></metadata><tags><tag>computer-parsed</tag><tag>unverified</tag></tags></law>