<?xml version="1.0" encoding="UTF-8"?><law><structure><unit label="title" identifier="XIII" order_by="13">EDUCATION</unit><unit label="chapter" identifier="161" order_by="161">SCHOOL EMPLOYEES -- TEACHERS' RETIREMENT AND TENURE </unit></structure><section_number>161.608</section_number><catch_line>Computation of benefits of member who has an account with another state system. </catch_line><order_by>608</order_by><text>The provisions of KRS 61.680 are hereby recognized and shall be followed in computing benefits of any member of the Teachers' Retirement System who also has an account with the Kentucky Employees Retirement System, County Employees Retirement System, or State Police Retirement System. </text><history>Repealed and reenacted 1990 Ky. Acts ch. 476, Pt. V, sec. 528, effective July 13, 1990. -- Created 1974 Ky. Acts ch. 128, sec. 38, effective March 26, 1974. </history><metadata><effective>July 13, 1990 </effective><pdf-author>ganesan_m</pdf-author><pdf-creation-date>2015-07-02</pdf-creation-date><pdf-download-date>2016-03-18 12:16:51</pdf-download-date><original-link>http://www.lrc.ky.gov/statutes/statute.aspx?id=3960</original-link></metadata><tags><tag>computer-parsed</tag><tag>unverified</tag></tags></law>