<?xml version="1.0" encoding="UTF-8"?><law><structure><unit label="title" identifier="XXV" order_by="25">BUSINESS AND FINANCIAL INSTITUTIONS</unit><unit label="chapter" identifier="" order_by=""></unit></structure><section_number>304.32-040</section_number><catch_line>Incorporation. </catch_line><order_by>32-040</order_by><text>KRS Chapter 273, as may from time to time be amended, except where inconsistent with the express provisions of this subtitle, shall govern the corporate powers, duties, and relationships of corporations incorporated under the provisions of this subtitle, but such chapter shall not apply to any corporation incorporated and formed under the laws of this state and in existence on June 18, 1970. </text><history>Created 1970 Ky. Acts ch. 301, subtit. 32, sec. 4, effective June 18, 1970. </history><metadata><effective>June 18, 1970 </effective><pdf-author>ganesan_m</pdf-author><pdf-creation-date>2015-07-02</pdf-creation-date><pdf-download-date>2016-03-18 12:16:06</pdf-download-date><original-link>http://www.lrc.ky.gov/statutes/statute.aspx?id=29761</original-link></metadata><tags><tag>computer-parsed</tag><tag>unverified</tag></tags></law>