<?xml version="1.0" encoding="UTF-8"?><law><structure><unit label="title" identifier="IX" order_by="9">COUNTIES, CITIES, AND OTHER LOCAL UNITS</unit><unit label="chapter" identifier="100" order_by="100">PLANNING AND ZONING </unit></structure><section_number>100.329</section_number><catch_line>Recording of plats. </catch_line><order_by>329</order_by><text>All final plats approved by the planning commission shall be recorded at the expense of the applicant in the office of the county clerk. A copy of all regulations and the official maps of each planning unit shall be filed with the appropriate agency as provided in this chapter, or as otherwise provided by law. </text><history>Amended 1988 Ky. Acts ch. 30, sec. 7, effective July 15, 1988. -- Amended 1978 Ky. Acts ch. 384, sec. 231, effective June 17, 1978. -- Created 1966 Ky. Acts ch. 172, sec. 88. </history><metadata><effective>July 15, 1988 </effective><former-codification> KRS 100.344.</former-codification><lrc-note>(1982).  A technical correction has been made in this section by the Reviser of Statutes pursuant to KRS 7.136. </lrc-note><pdf-author>ganesan_m</pdf-author><pdf-creation-date>2015-07-02</pdf-creation-date><pdf-download-date>2016-03-18 12:17:12</pdf-download-date><original-link>http://www.lrc.ky.gov/statutes/statute.aspx?id=26783</original-link></metadata><tags><tag>computer-parsed</tag><tag>unverified</tag></tags></law>