<?xml version="1.0" encoding="UTF-8"?><law><structure><unit label="title" identifier="XVII" order_by="17">ECONOMIC SECURITY AND PUBLIC WELFARE</unit><unit label="chapter" identifier="207" order_by="207">AID TO THE NEEDY BLIND -- EQUAL OPPORTUNITIES </unit></structure><section_number>207.220</section_number><catch_line>Cities and counties may adopt antidiscrimination measures. </catch_line><order_by>220</order_by><text>Cities and counties may adopt and enforce, or authorize commissions or agencies to enforce ordinances, orders, and resolutions prohibiting unfair treatment of individuals on the basis of physical disability, and may prescribe penalties for violation thereof, such penalties being in addition to those herein authorized. </text><history> Amended 1994 Ky. Acts ch. 405, sec. 69, effective July 15, 1994. -- Created 1976 Ky. Acts ch. 280, sec. 11. </history><metadata><effective> July 15, 1994 </effective><pdf-author>ganesan_m</pdf-author><pdf-creation-date>2015-07-02</pdf-creation-date><pdf-download-date>2016-03-18 12:16:40</pdf-download-date><original-link>http://www.lrc.ky.gov/statutes/statute.aspx?id=7925</original-link></metadata><tags><tag>computer-parsed</tag><tag>unverified</tag></tags></law>