<?xml version="1.0" encoding="UTF-8"?><law><structure><unit label="title" identifier="XV" order_by="15">ROADS, WATERWAYS, AND AVIATION</unit><unit label="chapter" identifier="177" order_by="177">STATE AND FEDERAL HIGHWAYS -- LIMITED ACCESS FACILITIES -- TURNPIKES -- ROAD BONDS -- BILLBOARDS -- RECYCLERS </unit></structure><section_number>177.520</section_number><catch_line>Turnpike bonds valid for purposes of investment or collateral. </catch_line><order_by>520</order_by><text>Bonds issued by the department under the provisions of KRS 177.390 to 177.570 are hereby made securities in which all public officers and public bodies, agencies and instrumentalities of the Commonwealth and its political subdivisions, all insurance companies, trust companies, banking associations, investment companies, executors, administrators, trustees and other fiduciaries, and all other persons whatsoever who are now or may hereafter be authorized to invest in bonds or other obligations of a similar nature may properly and legally invest funds, including capital in their control or belonging to them. Such bonds are hereby made securities which may properly and legally be deposited with and received by any state or municipal officer or any agency or political subdivision of the Commonwealth for any purpose for which the deposit of bonds or other obligations of the Commonwealth is now or may hereafter be authorized by law. </text><history>Amended 1960 Ky. Acts ch. 174, sec. 8, effective March 25, 1960. -- Created 1950 Ky. Acts ch. 157, sec. 14. </history><metadata><effective>March 25, 1960 </effective><pdf-author>ganesan_m</pdf-author><pdf-creation-date>2015-07-02</pdf-creation-date><pdf-download-date>2016-03-18 12:16:50</pdf-download-date><original-link>http://www.lrc.ky.gov/statutes/statute.aspx?id=5338</original-link></metadata><tags><tag>computer-parsed</tag><tag>unverified</tag></tags></law>